aioworkers_boto/__about__.py
aioworkers_boto/__about__.pyi
aioworkers_boto/__init__.py
aioworkers_boto/__init__.pyi
aioworkers_boto/core.py
aioworkers_boto/core.pyi
aioworkers_boto/py.typed
aioworkers_boto/storage.py
aioworkers_boto/storage.pyi
aioworkers_boto-0.1.0.dist-info/METADATA
aioworkers_boto-0.1.0.dist-info/WHEEL
aioworkers_boto-0.1.0.dist-info/licenses/LICENSE.txt
aioworkers_boto-0.1.0.dist-info/RECORD
