Metadata-Version: 2.1
Name: aioworkers-boto
Version: 0.1.0
Summary: Connector and storage over boto
Project-URL: Documentation, https://github.com/aioworkers/aioworkers-boto#readme
Project-URL: Issues, https://github.com/aioworkers/aioworkers-boto/issues
Project-URL: Source, https://github.com/aioworkers/aioworkers-boto
Author-email: Alexander Malev <malev@somedev.ru>
License-File: LICENSE.txt
Keywords: aioworkers,boto,botocore,s3
Classifier: Development Status :: 5 - Production/Stable
Classifier: Framework :: AsyncIO
Classifier: Programming Language :: Python
Classifier: Programming Language :: Python :: 3.7
Classifier: Programming Language :: Python :: 3.8
Classifier: Programming Language :: Python :: 3.9
Classifier: Programming Language :: Python :: 3.10
Classifier: Programming Language :: Python :: Implementation :: CPython
Classifier: Programming Language :: Python :: Implementation :: PyPy
Requires-Python: >=3.7
Requires-Dist: aiobotocore
Requires-Dist: aioworkers
